pydesk/__init__.py
pydesk/desktop.py
pydesk-0.0.1.dist-info/LICENSE.txt
pydesk-0.0.1.dist-info/METADATA
pydesk-0.0.1.dist-info/RECORD
pydesk-0.0.1.dist-info/WHEEL
pydesk-0.0.1.dist-info/entry_points.txt
pydesk-0.0.1.dist-info/top_level.txt
